dragdrag/__init__.py
dragdrag/app.py
templates/index.html
dragdrag-0.1.0.dist-info/METADATA
dragdrag-0.1.0.dist-info/WHEEL
dragdrag-0.1.0.dist-info/entry_points.txt
dragdrag-0.1.0.dist-info/top_level.txt
dragdrag-0.1.0.dist-info/RECORD
