Metadata-Version: 2.1
Name: dragdrag
Version: 0.1.0
Summary: 局域网文件拖拽上传/下载/删除的Web应用
Author: 你的名字
Author-email: your@email.com
Requires-Python: >=3.6
Requires-Dist: Flask
Requires-Dist: Werkzeug
